tfduck/__init__.py
tfduck/main.py
tfduck/bdp_sdk_py/__init__.py
tfduck/bdp_sdk_py/example.py
tfduck/bdp_sdk_py/config/__init__.py
tfduck/bdp_sdk_py/config/bdpmanager.py
tfduck/bdp_sdk_py/config/table_config.py
tfduck/bdp_sdk_py/opends/__init__.py
tfduck/bdp_sdk_py/opends/opends.py
tfduck/bdp_sdk_py/opends/sdk.py
tfduck/common/__init__.py
tfduck/common/defines.py
tfduck/common/defines_clean.py
tfduck/common/extendEncoder.py
tfduck/oss/__init__.py
tfduck/oss/oss.py
tfduck/pyspark_k8s/__init__.py
tfduck/pyspark_k8s/k8s_manage.py
tfduck/pyspark_k8s/spark_manage.py
tfduck/s3/__init__.py
tfduck/s3/s3oper.py
tfduck/sagemaker/__init__.py
tfduck/sagemaker/saoper.py
tfduck/serverless_k8s/__init__.py
tfduck/serverless_k8s/k8s_manage.py
tfduck/serverless_k8s/k8s_task.py
tfduck/tga/__init__.py
tfduck/tga/base_tga.py
tfduck/tga/predict_sql_ltv.py
tfduck/tga/predict_sql_retain.py
tfduck/tga/predict_sql_yh.py
tfduck/tga/tga.py
tfduck/tga/tga_test.py
tfduck/tga/tga_trino.py
tfduck/tga/train_sql_ltv.py
tfduck/tga/train_sql_retain.py
tfduck/tga/train_sql_yh.py
tfduck/thinkdata/__init__.py
tfduck/thinkdata/query.py
tfduck_bsd-0.20.1.data/scripts/tfduck
tfduck_bsd-0.20.1.dist-info/LICENSE
tfduck_bsd-0.20.1.dist-info/METADATA
tfduck_bsd-0.20.1.dist-info/WHEEL
tfduck_bsd-0.20.1.dist-info/top_level.txt
tfduck_bsd-0.20.1.dist-info/RECORD
