Metadata-Version: 2.1
Name: tfduck-bsd
Version: 0.20.1
Summary: A small example package
Home-page: UNKNOWN
Author: yuanxiao
Author-email: yuan6785@163.com
License: UNKNOWN
Platform: UNKNOWN
Classifier: Programming Language :: Python :: 3
Classifier: License :: OSI Approved :: MIT License
Classifier: Operating System :: OS Independent
Requires-Python: >=3.5
License-File: LICENSE
Requires-Dist: arrow (>=0.15.5)
Requires-Dist: requests (>=2.20.0)
Requires-Dist: django (==2.2.12)
Requires-Dist: oss2 (==2.15.0)
Requires-Dist: ThinkingDataSdk (==1.8.0)
Requires-Dist: kubernetes (==12.0.1)
Requires-Dist: sagemaker (==2.183.0)
Requires-Dist: boto3 (==1.28.49)
Requires-Dist: trino (==0.327.0)
